iati_sphinx_theme/__init__.py
iati_sphinx_theme/footer.html
iati_sphinx_theme/globaltoc.html
iati_sphinx_theme/header.html
iati_sphinx_theme/language-switcher.html
iati_sphinx_theme/layout.html
iati_sphinx_theme/page.html
iati_sphinx_theme/relations.html
iati_sphinx_theme/search.html
iati_sphinx_theme/theme.conf
iati_sphinx_theme/locale/sphinx.pot
iati_sphinx_theme/locale/es/LC_MESSAGES/sphinx.po
iati_sphinx_theme/locale/fr/LC_MESSAGES/sphinx.po
iati_sphinx_theme/static/.gitignore
iati_sphinx_theme/static/favicon-16x16.png
iati_sphinx_theme/static/language-switcher.js
iati_sphinx_theme/static/logo-colour.svg
iati_sphinx_theme/static/css/style.css
iati_sphinx_theme-3.1.1.dist-info/entry_points.txt
iati_sphinx_theme-3.1.1.dist-info/WHEEL
iati_sphinx_theme-3.1.1.dist-info/METADATA
iati_sphinx_theme-3.1.1.dist-info/RECORD
