Metadata-Version: 2.4
Name: iati-sphinx-theme
Version: 3.1.1
Summary: A sphinx theme for IATI documentation sites.
Requires-Dist: black ; extra == "dev"
Requires-Dist: debugpy ; extra == "dev"
Requires-Dist: iati-sphinx-theme[docs] ; extra == "dev"
Requires-Dist: isort ; extra == "dev"
Requires-Dist: flake8 ; extra == "dev"
Requires-Dist: Flake8-pyproject ; extra == "dev"
Requires-Dist: mypy ; extra == "dev"
Requires-Dist: sphinx-autobuild ; extra == "dev"
Requires-Dist: sphinx-intl ; extra == "dev"
Requires-Dist: types-docutils ; extra == "dev"
Requires-Dist: sphinxcontrib-video ; extra == "docs"
Requires-Dist: sphinxcontrib-youtube ; extra == "docs"
Provides-Extra: dev
Provides-Extra: docs
